setup.py
django_finalware.egg-info/PKG-INFO
django_finalware.egg-info/SOURCES.txt
django_finalware.egg-info/dependency_links.txt
django_finalware.egg-info/top_level.txt
finalware/__init__.py
finalware/admin.py
finalware/apps.py
finalware/context_processors.py
finalware/defaults.py
finalware/models.py
finalware/receivers.py
finalware/utils.py
finalware/tests/__init__.py
finalware/tests/settings.py
finalware/tests/tests.py
finalware/tests/urls.py
finalware/tests/views.py
finalware/tests/templates/finalware/context_processors.html