Metadata-Version: 1.1
Name: django-finalware
Version: 0.1.4
Summary: A utility application that finalizes the bootstrapping of a Django-powered site
Home-page: https://github.com/un33k/django-finalware
Author: Val Neekman
Author-email: info@neekware.com
License: BSD
Platform: UNKNOWN
Classifier: Development Status :: 4 - Beta
Classifier: Environment :: Web Environment
Classifier: Intended Audience :: Developers
Classifier: License :: OSI Approved :: BSD License
Classifier: Operating System :: OS Independent
Classifier: Programming Language :: Python
Classifier: Topic :: Utilities
